{
  "name": "Leading Swipe",
  "facts": [
    {
      "text": "Range",
      "type": "Range",
      "icon": "https://render.guildwars2.com/file/0AAB34BEB1C9F4A25EC612DDBEACF3E20B2810FA/156666.png",
      "value": 130
    },
    {
      "text": "Apply Buff/Condition",
      "type": "Buff",
      "icon": "https://render.guildwars2.com/file/79FF0046A5F9ADA3B4C4EC19ADB4CB124D5F0021/102848.png",
      "duration": 4,
      "status": "Bleeding",
      "description": "Deals damage every second; stacks intensity.",
      "apply_count": 1
    },
    {
      "text": "Damage",
      "type": "Damage",
      "icon": "https://render.guildwars2.com/file/61AA4919C4A7990903241B680A69530121E994C7/156657.png",
      "hit_count": 1,
      "dmg_multiplier": 0.42
    },
    {
      "text": "Number of Targets",
      "type": "Number",
      "icon": "https://render.guildwars2.com/file/BBE8191A494B0352259C10EADFDACCE177E6DA5B/1770208.png",
      "value": 2
    }
  ],
  "description": "Rake your dagger across your foe, leaving them bleeding.",
  "icon": "https://render.guildwars2.com/file/EDDA7CC00BAEB5EEE53A0D2937CDB10094A29692/1770554.png",
  "type": "Weapon",
  "weapon_type": "Dagger",
  "professions": [
    "Ranger"
  ],
  "slot": "Weapon_1",
  "next_chain": 41800,
  "prev_chain": 45426,
  "flip_skill": 41800,
  "flags": [
    "NoUnderwater"
  ],
  "specialization": 55,
  "id": 40301,
  "chat_link": "[&Bm2dAAA=]"
}