{
  "name": "Blazing Edge",
  "facts": [
    {
      "text": "Range",
      "type": "Range",
      "icon": "https://render.guildwars2.com/file/0AAB34BEB1C9F4A25EC612DDBEACF3E20B2810FA/156666.png",
      "value": 600
    },
    {
      "text": "Recharge",
      "type": "Recharge",
      "icon": "https://render.guildwars2.com/file/D767B963D120F077C3B163A05DC05A7317D7DB70/156651.png",
      "value": 12
    },
    {
      "text": "Damage",
      "type": "Damage",
      "icon": "https://render.guildwars2.com/file/61AA4919C4A7990903241B680A69530121E994C7/156657.png",
      "hit_count": 1,
      "dmg_multiplier": 0.8
    },
    {
      "text": "Apply Buff/Condition",
      "type": "Buff",
      "icon": "https://render.guildwars2.com/file/B47BF5803FED2718D7474EAF9617629AD068EE10/102849.png",
      "duration": 3,
      "status": "Burning",
      "description": "Deals damage every second; stacks intensity.",
      "apply_count": 1
    },
    {
      "text": "Number of Targets",
      "type": "Number",
      "icon": "https://render.guildwars2.com/file/BBE8191A494B0352259C10EADFDACCE177E6DA5B/1770208.png",
      "value": 3
    },
    {
      "text": "Pull",
      "type": "Number",
      "icon": "https://render.guildwars2.com/file/B0CD8077991E4FB1622D2930337ED7F9B54211D5/156665.png",
      "value": 600
    }
  ],
  "description": "Conjure a magical axe to rake your enemies toward you.",
  "icon": "https://render.guildwars2.com/file/B254F2279C5C1E9E6E3AAE11B97D460E0F3E45E0/1770459.png",
  "type": "Weapon",
  "weapon_type": "Axe",
  "professions": [
    "Guardian"
  ],
  "slot": "Weapon_3",
  "flags": [
    "NoUnderwater"
  ],
  "specialization": 62,
  "id": 45402,
  "chat_link": "[&BlqxAAA=]"
}