{
  "name": "Blowtorch",
  "facts": [
    {
      "text": "Range",
      "type": "Range",
      "icon": "https://render.guildwars2.com/file/0AAB34BEB1C9F4A25EC612DDBEACF3E20B2810FA/156666.png",
      "value": 600
    },
    {
      "text": "Recharge",
      "type": "Recharge",
      "icon": "https://render.guildwars2.com/file/D767B963D120F077C3B163A05DC05A7317D7DB70/156651.png",
      "value": 12
    },
    {
      "text": "Maximum Damage",
      "type": "Damage",
      "icon": "https://render.guildwars2.com/file/61AA4919C4A7990903241B680A69530121E994C7/156657.png",
      "hit_count": 1,
      "dmg_multiplier": 1
    },
    {
      "text": "Minimum Damage",
      "type": "Damage",
      "icon": "https://render.guildwars2.com/file/61AA4919C4A7990903241B680A69530121E994C7/156657.png",
      "hit_count": 1,
      "dmg_multiplier": 0.33
    },
    {
      "text": "Apply Buff/Condition",
      "type": "Buff",
      "icon": "https://render.guildwars2.com/file/B47BF5803FED2718D7474EAF9617629AD068EE10/102849.png",
      "duration": 6,
      "status": "Burning",
      "description": "Deals damage every second; stacks intensity.",
      "apply_count": 4
    },
    {
      "text": "Apply Buff/Condition",
      "type": "Buff",
      "icon": "https://render.guildwars2.com/file/B47BF5803FED2718D7474EAF9617629AD068EE10/102849.png",
      "duration": 3,
      "status": "Burning",
      "description": "Deals damage every second; stacks intensity.",
      "apply_count": 4
    },
    {
      "text": "Number of Targets",
      "type": "Number",
      "icon": "https://render.guildwars2.com/file/BBE8191A494B0352259C10EADFDACCE177E6DA5B/1770208.png",
      "value": 3
    },
    {
      "text": "Apply Buff/Condition",
      "type": "Buff",
      "icon": "https://render.guildwars2.com/file/B47BF5803FED2718D7474EAF9617629AD068EE10/102849.png",
      "duration": 12,
      "status": "Burning",
      "description": "Deals damage every second; stacks intensity.",
      "apply_count": 2
    },
    {
      "text": "Apply Buff/Condition",
      "type": "Buff",
      "icon": "https://render.guildwars2.com/file/B47BF5803FED2718D7474EAF9617629AD068EE10/102849.png",
      "duration": 6,
      "status": "Burning",
      "description": "Deals damage every second; stacks intensity.",
      "apply_count": 2
    }
  ],
  "description": "Unleash flames from your pistol to burn foes. Deals more damage the closer you are.",
  "icon": "https://render.guildwars2.com/file/061D48DCAC954D91D8F8BD7F6B193201A695F92F/103407.png",
  "type": "Weapon",
  "weapon_type": "Pistol",
  "professions": [
    "Engineer"
  ],
  "slot": "Weapon_4",
  "flags": [
    "NoUnderwater"
  ],
  "id": 5831,
  "chat_link": "[&BscWAAA=]",
  "traited_facts": [
    {
      "text": "Apply Buff/Condition",
      "type": "Buff",
      "icon": "https://render.guildwars2.com/file/B47BF5803FED2718D7474EAF9617629AD068EE10/102849.png",
      "duration": 8,
      "status": "Burning",
      "description": "Deals damage every second; stacks intensity.",
      "apply_count": 4,
      "requires_trait": 1878,
      "overrides": 4
    },
    {
      "text": "Apply Buff/Condition",
      "type": "Buff",
      "icon": "https://render.guildwars2.com/file/B47BF5803FED2718D7474EAF9617629AD068EE10/102849.png",
      "duration": 4,
      "status": "Burning",
      "description": "Deals damage every second; stacks intensity.",
      "apply_count": 4,
      "requires_trait": 1878,
      "overrides": 5
    },
    {
      "text": "Apply Buff/Condition",
      "type": "Buff",
      "icon": "https://render.guildwars2.com/file/B47BF5803FED2718D7474EAF9617629AD068EE10/102849.png",
      "duration": 16,
      "status": "Burning",
      "description": "Deals damage every second; stacks intensity.",
      "apply_count": 2,
      "requires_trait": 1878,
      "overrides": 7
    },
    {
      "text": "Apply Buff/Condition",
      "type": "Buff",
      "icon": "https://render.guildwars2.com/file/B47BF5803FED2718D7474EAF9617629AD068EE10/102849.png",
      "duration": 8,
      "status": "Burning",
      "description": "Deals damage every second; stacks intensity.",
      "apply_count": 2,
      "requires_trait": 1878,
      "overrides": 8
    }
  ]
}