{
  "name": "Air Blast",
  "facts": [
    {
      "text": "Range",
      "type": "Range",
      "icon": "https://render.guildwars2.com/file/0AAB34BEB1C9F4A25EC612DDBEACF3E20B2810FA/156666.png",
      "value": 300
    },
    {
      "text": "Recharge",
      "type": "Recharge",
      "icon": "https://render.guildwars2.com/file/D767B963D120F077C3B163A05DC05A7317D7DB70/156651.png",
      "value": 15
    },
    {
      "text": "Knockback Distance",
      "type": "Distance",
      "icon": "https://render.guildwars2.com/file/9A6A02DCA260929CD14B4A4402266006981FF51B/648509.png",
      "distance": 400
    },
    {
      "text": "Number of Targets",
      "type": "Number",
      "icon": "https://render.guildwars2.com/file/BBE8191A494B0352259C10EADFDACCE177E6DA5B/1770208.png",
      "value": 5
    },
    {
      "text": "Apply Buff/Condition",
      "type": "Buff",
      "icon": "https://render.guildwars2.com/file/B47BF5803FED2718D7474EAF9617629AD068EE10/102849.png",
      "duration": 2,
      "status": "Burning",
      "description": "Deals damage every second; stacks intensity.",
      "apply_count": 2
    }
  ],
  "description": "Push back foes and projectiles with a hot-air blast, burning foes that are already on fire.",
  "icon": "https://render.guildwars2.com/file/92CE7EBBFA670CB00809F8267802A6FA459E2EC8/103291.png",
  "type": "Bundle",
  "weapon_type": "None",
  "professions": [
    "Thief",
    "Mesmer",
    "Warrior",
    "Elementalist",
    "Necromancer",
    "Guardian",
    "Ranger",
    "Engineer",
    "Revenant"
  ],
  "slot": "Weapon_3",
  "flags": [
    "NoUnderwater"
  ],
  "id": 5930,
  "chat_link": "[&BioXAAA=]"
}