{
  "name": "Core Reactor Shot",
  "facts": [
    {
      "text": "Range",
      "type": "Range",
      "icon": "https://render.guildwars2.com/file/0AAB34BEB1C9F4A25EC612DDBEACF3E20B2810FA/156666.png",
      "value": 1200
    },
    {
      "text": "Recharge",
      "type": "Recharge",
      "icon": "https://render.guildwars2.com/file/D767B963D120F077C3B163A05DC05A7317D7DB70/156651.png",
      "value": 25
    },
    {
      "text": "Damage",
      "type": "Damage",
      "icon": "https://render.guildwars2.com/file/61AA4919C4A7990903241B680A69530121E994C7/156657.png",
      "hit_count": 1,
      "dmg_multiplier": 2.5
    },
    {
      "text": "Launch",
      "type": "Distance",
      "icon": "https://render.guildwars2.com/file/B4087CEB5CC006172E0A09DADC5452807A0CA3F7/2440712.png",
      "distance": 240
    },
    {
      "text": "Number of Targets",
      "type": "Number",
      "icon": "https://render.guildwars2.com/file/BBE8191A494B0352259C10EADFDACCE177E6DA5B/1770208.png",
      "value": 5
    },
    {
      "text": "Radius",
      "type": "Distance",
      "icon": "https://render.guildwars2.com/file/B0CD8077991E4FB1622D2930337ED7F9B54211D5/156665.png",
      "distance": 240
    }
  ],
  "description": "Mech Command. Charge up and then release a powerful ball of jade energy at your target that explodes on contact.",
  "icon": "https://render.guildwars2.com/file/7D28F26BB09378C256BAAE2F90DA1F3D6B5CCB71/2503683.png",
  "flags": [],
  "id": 63345,
  "chat_link": "[&BnH3AAA=]"
}