{
  "name": "Maul",
  "facts": [
    {
      "text": "Range",
      "type": "Range",
      "icon": "https://render.guildwars2.com/file/0AAB34BEB1C9F4A25EC612DDBEACF3E20B2810FA/156666.png",
      "value": 130
    },
    {
      "text": "Recharge",
      "type": "Recharge",
      "icon": "https://render.guildwars2.com/file/D767B963D120F077C3B163A05DC05A7317D7DB70/156651.png",
      "value": 12
    },
    {
      "text": "Damage",
      "type": "Damage",
      "icon": "https://render.guildwars2.com/file/61AA4919C4A7990903241B680A69530121E994C7/156657.png",
      "hit_count": 2,
      "dmg_multiplier": 1.1
    },
    {
      "text": "Apply Buff/Condition",
      "type": "Buff",
      "icon": "https://render.guildwars2.com/file/79FF0046A5F9ADA3B4C4EC19ADB4CB124D5F0021/102848.png",
      "duration": 6,
      "status": "Bleeding",
      "description": "Deals damage every second; stacks intensity.",
      "apply_count": 2
    }
  ],
  "description": "Maul your foes and make them bleed.",
  "icon": "https://render.guildwars2.com/file/24073F5A0566ABE32DFB74204E9FA01025D85D71/104055.png",
  "type": "Profession",
  "weapon_type": "None",
  "professions": [
    "Ranger"
  ],
  "slot": "Profession_1",
  "flags": [
    "NoUnderwater"
  ],
  "specialization": 55,
  "id": 41406,
  "chat_link": "[&Br6hAAA=]"
}