{
  "name": "Unravel",
  "facts": [
    {
      "text": "Recharge",
      "type": "Recharge",
      "icon": "https://render.guildwars2.com/file/D767B963D120F077C3B163A05DC05A7317D7DB70/156651.png",
      "value": 5
    },
    {
      "text": "Apply Buff/Condition",
      "type": "Buff",
      "icon": "https://render.guildwars2.com/file/A3E26A4A4FF0C974B4AAACA6B310060CFBC2D007/1770330.png",
      "duration": 5,
      "status": "Unravel",
      "description": "Fully attune to elements and temporarily lose dual attacks.",
      "apply_count": 1
    },
    {
      "text": "Maximum Count",
      "type": "Number",
      "icon": "https://render.guildwars2.com/file/B4490FB81AA1E7C06F1B22056AE09A0F54CBE2C4/1770201.png",
      "value": 2
    },
    {
      "text": "Count Recharge",
      "type": "Time",
      "icon": "https://render.guildwars2.com/file/AAB7C5387A08367C2F023F19FEE70E1556AD4375/1770202.png",
      "duration": 25
    },
    {
      "text": "Apply Buff/Condition",
      "type": "PrefixedBuff",
      "icon": "https://render.guildwars2.com/file/2FA9DF9D6BC17839BBEA14723F1C53D645DDB5E1/102852.png",
      "duration": 5,
      "status": "Might",
      "description": "Increased outgoing damage; stacks intensity.",
      "apply_count": 5,
      "prefix": {
        "text": "Apply Buff/Condition",
        "icon": "https://render.guildwars2.com/file/1C91E9C799469ACC6EAF1ACD4B0AD8ACAB0C69A2/103035.png",
        "status": "Fire Attunement",
        "description": "Cast fire spells."
      }
    },
    {
      "text": "Apply Buff/Condition",
      "type": "PrefixedBuff",
      "icon": "https://render.guildwars2.com/file/58E92EBAF0DB4DA7C4AC04D9B22BCA5ECF0100DE/102843.png",
      "duration": 5,
      "status": "Vigor",
      "description": "Endurance regeneration increased by 50%; stacks duration.",
      "apply_count": 1,
      "prefix": {
        "text": "Apply Buff/Condition",
        "icon": "https://render.guildwars2.com/file/737E1B9F7855B9F5D3DE1C990CD42118EF3D1C92/102820.png",
        "status": "Water Attunement",
        "description": "Cast water spells."
      }
    },
    {
      "text": "Apply Buff/Condition",
      "type": "PrefixedBuff",
      "icon": "https://render.guildwars2.com/file/96D90DF84CAFE008233DD1C2606A12C1A0E68048/102842.png",
      "duration": 5,
      "status": "Fury",
      "description": "Critical chance increased; stacks duration.",
      "apply_count": 1,
      "prefix": {
        "text": "Apply Buff/Condition",
        "icon": "https://render.guildwars2.com/file/4857F59020DE3B0950B9C91F3D234A1C1932984A/103048.png",
        "status": "Air Attunement",
        "description": "Cast air spells."
      }
    },
    {
      "text": "Apply Buff/Condition",
      "type": "PrefixedBuff",
      "icon": "https://render.guildwars2.com/file/CD77D1FAB7B270223538A8F8ECDA1CFB044D65F4/102834.png",
      "duration": 5,
      "status": "Protection",
      "description": "Incoming strike damage decreased by 33%; stacks duration.",
      "apply_count": 1,
      "prefix": {
        "text": "Apply Buff/Condition",
        "icon": "https://render.guildwars2.com/file/4B8056D9BD080DC8E74AE6A57B2B383A2D4265C9/102870.png",
        "status": "Earth Attunement",
        "description": "Cast earth spells."
      }
    },
    {
      "text": "Recharge Reduced",
      "type": "Percent",
      "icon": "https://render.guildwars2.com/file/AAB7C5387A08367C2F023F19FEE70E1556AD4375/1770202.png",
      "percent": 100
    }
  ],
  "description": "Stance. For a period of time, you forego your weaver training, choosing to fully attune to elements instead. Gain boons based on your primary attunement, and reduce all attunement cooldowns.",
  "icon": "https://render.guildwars2.com/file/A3E26A4A4FF0C974B4AAACA6B310060CFBC2D007/1770330.png",
  "type": "Utility",
  "weapon_type": "None",
  "professions": [
    "Elementalist"
  ],
  "slot": "Utility",
  "flags": [],
  "specialization": 56,
  "id": 44612,
  "chat_link": "[&BkSuAAA=]",
  "categories": [
    "Stance"
  ]
}